geoserver_pyadm/__init__.py
geoserver_pyadm/__main__.py
geoserver_pyadm/_auth.py
geoserver_pyadm/_exceptions.py
geoserver_pyadm/datastore.py
geoserver_pyadm/geoserver.py
geoserver_pyadm/info.py
geoserver_pyadm/layer.py
geoserver_pyadm/style.py
geoserver_pyadm/upload.py
geoserver_pyadm/workspace.py
geoserver_pyadm/test/importer.py
geoserver_pyadm/test/test-add-and-upload-style.py
geoserver_pyadm/test/test-create-store.py
geoserver_pyadm/test/test-create-workspace.py
geoserver_pyadm/test/test-delete-layer.py
geoserver_pyadm/test/test-delete-store.py
geoserver_pyadm/test/test-delete-style.py
geoserver_pyadm/test/test-delete-workspace.py
geoserver_pyadm/test/test-get-functions.py
geoserver_pyadm/test/test-get-settings.py
geoserver_pyadm/test/test-modify-style.py
geoserver_pyadm/test/test-publish-raster-layer-on-server.py
geoserver_pyadm/test/test-publish-shapefiles-on-server.py
geoserver_pyadm/test/test-set-styles.py
geoserver_pyadm/test/test-upload-geopackage.py
geoserver_pyadm/test/test-upload-local-raster.py
geoserver_pyadm/test/test-upload-local-shapefiles.py
geoserver_pyadm-1.0.1.dist-info/LICENSE
geoserver_pyadm-1.0.1.dist-info/METADATA
geoserver_pyadm-1.0.1.dist-info/WHEEL
geoserver_pyadm-1.0.1.dist-info/entry_points.txt
geoserver_pyadm-1.0.1.dist-info/top_level.txt
geoserver_pyadm-1.0.1.dist-info/RECORD
